aiohttp_rate_limiter/__init__.py
aiohttp_rate_limiter/cfg.py
aiohttp_rate_limiter/limiters/__init__.py
aiohttp_rate_limiter/limiters/fixed_window.py
aiohttp_rate_limiter/limiters/leaky_bucket.py
aiohttp_rate_limiter/limiters/sliding_log.py
aiohttp_rate_limiter/limiters/sliding_window.py
aiohttp_rate_limiter-0.0.4.dist-info/LICENSE
aiohttp_rate_limiter-0.0.4.dist-info/METADATA
aiohttp_rate_limiter-0.0.4.dist-info/WHEEL
aiohttp_rate_limiter-0.0.4.dist-info/top_level.txt
aiohttp_rate_limiter-0.0.4.dist-info/RECORD
