Metadata-Version: 2.1
Name: aiohttp-rate-limiter
Version: 0.0.4
Summary: A library for control and limiting requests with aiohttp framework
Home-page: https://github.com/Flacy/aiohttp-rate-limiter
Author: Flacy
Author-email: me@flacy.me
License: UNKNOWN
Platform: UNKNOWN
Classifier: Programming Language :: Python :: 3
Classifier: Operating System :: OS Independent
Classifier: Development Status :: 3 - Alpha
Requires-Python: >=3.7
Requires-Dist: aiohttp (<4.0.0)
